yflog/__init__.py
yflog-1.0.0.dist-info/LICENSE
yflog-1.0.0.dist-info/METADATA
yflog-1.0.0.dist-info/WHEEL
yflog-1.0.0.dist-info/top_level.txt
yflog-1.0.0.dist-info/RECORD
