Metadata-Version: 2.1
Name: yflog
Version: 1.0.0
Summary: A simple logger used in python program.
Home-page: https://github.com/moshangsang24/yflog
Author: moshangsang24
Author-email: liuyifan731@163.com
Classifier: Programming Language :: Python :: 3
Classifier: License :: OSI Approved :: MIT License
Classifier: Operating System :: OS Independent
License-File: LICENSE
